web3_google_hsm/__init__.py
web3_google_hsm/__version__.py
web3_google_hsm/_cli.py
web3_google_hsm/config.py
web3_google_hsm/exceptions.py
web3_google_hsm/utils.py
web3_google_hsm/accounts/__init__.py
web3_google_hsm/accounts/gcp_kms_account.py
web3_google_hsm/types/__init__.py
web3_google_hsm/types/ethereum_types.py
web3_google_hsm-0.1.0.dist-info/METADATA
web3_google_hsm-0.1.0.dist-info/WHEEL
web3_google_hsm-0.1.0.dist-info/entry_points.txt
web3_google_hsm-0.1.0.dist-info/licenses/AUTHORS.md
web3_google_hsm-0.1.0.dist-info/licenses/LICENSE
web3_google_hsm-0.1.0.dist-info/RECORD
