Metadata-Version: 2.4
Name: web3-google-hsm
Version: 0.1.0
Summary: Cloud HSM to sign Web3.py Ethereum transactions
Project-URL: Documentation, https://Aviksaikat.github.io/web3-google-hsm/
Project-URL: Source, https://github.com/Ankvik-Tech-Labs/web3-google-hsm
Author-email: web3-google-hsm <github.maturity983@passinbox.com>
License: BSD 3-Clause License
License-File: AUTHORS.md
License-File: LICENSE
Classifier: Programming Language :: Python :: 3
Classifier: Programming Language :: Python :: 3.9
Classifier: Programming Language :: Python :: 3.10
Classifier: Programming Language :: Python :: 3.11
Classifier: Programming Language :: Python :: 3.12
Classifier: Programming Language :: Python :: 3.13
Classifier: Programming Language :: Python :: Implementation :: CPython
Classifier: Programming Language :: Python :: Implementation :: PyPy
Requires-Python: >=3.10
Requires-Dist: cryptography
Requires-Dist: ecdsa[gmpy2]
Requires-Dist: eth-account
Requires-Dist: eth-keys
Requires-Dist: eth-utils
Requires-Dist: google-cloud-kms
Requires-Dist: pydantic
Requires-Dist: pydantic-settings
Requires-Dist: typer
Provides-Extra: dev
Requires-Dist: ipython; extra == 'dev'
Requires-Dist: python-dotenv; extra == 'dev'
Requires-Dist: web3; extra == 'dev'
